skelet/__init__.py
skelet/errors.py
skelet/py.typed
skelet/storage.py
skelet/fields/__init__.py
skelet/fields/base.py
skelet/functions/__init__.py
skelet/functions/asdict.py
skelet/sources/__init__.py
skelet/sources/abstract.py
skelet/sources/cli.py
skelet/sources/collection.py
skelet/sources/env.py
skelet/sources/getter_for_libraries.py
skelet/sources/json.py
skelet/sources/memory.py
skelet/sources/toml.py
skelet/sources/yaml.py
skelet-0.0.5.dist-info/LICENSE
skelet-0.0.5.dist-info/METADATA
skelet-0.0.5.dist-info/WHEEL
skelet-0.0.5.dist-info/top_level.txt
skelet-0.0.5.dist-info/RECORD
