Metadata-Version: 2.1
Name: skelet
Version: 0.0.5
Summary: Collect all the settings in one place
Author-email: Evgeniy Blinov <zheni-b@yandex.ru>
Project-URL: Source, https://github.com/pomponchik/skelet
Project-URL: Tracker, https://github.com/pomponchik/skelet/issues
Keywords: settings,configs
Classifier: Operating System :: OS Independent
Classifier: Operating System :: MacOS :: MacOS X
Classifier: Operating System :: Microsoft :: Windows
Classifier: Operating System :: POSIX
Classifier: Operating System :: POSIX :: Linux
Classifier: Programming Language :: Python
Classifier: Programming Language :: Python :: 3.8
Classifier: Programming Language :: Python :: 3.9
Classifier: Programming Language :: Python :: 3.10
Classifier: Programming Language :: Python :: 3.11
Classifier: Programming Language :: Python :: 3.12
Classifier: Programming Language :: Python :: 3.13
Classifier: Programming Language :: Python :: 3.14
Classifier: License :: OSI Approved :: MIT License
Classifier: Intended Audience :: Developers
Classifier: Topic :: Software Development :: Libraries
Requires-Python: >=3.8
License-File: LICENSE
Requires-Dist: printo==0.0.8
Requires-Dist: locklib==0.0.18
Requires-Dist: simtypes>=0.0.10
Requires-Dist: pyyaml==6.0.3
Requires-Dist: types-pyyaml==6.0.12.20241230
Requires-Dist: denial>=0.0.6
Requires-Dist: tomli==2.3.0; python_version <= "3.12"
